HSbmi/bmi.py
HSbmi-0.0.0.1.dist-info/METADATA
HSbmi-0.0.0.1.dist-info/WHEEL
HSbmi-0.0.0.1.dist-info/top_level.txt
HSbmi-0.0.0.1.dist-info/RECORD
